<?xml version="1.0" encoding="UTF-8" ?>
<!DOCTYPE mapper PUBLIC "-//mybatis.org//DTD Mapper 3.0//EN" "http://mybatis.org/dtd/mybatis-3-mapper.dtd" >
<mapper namespace="com.ami.ec.channel.dao.pluginManager.IfDefineMapper" >
  <resultMap id="BaseResultMap" type="com.ami.ec.channel.domain.pluginManager.IfDefine" >
    <!--
      WARNING - @mbggenerated
      This element is automatically generated by MyBatis Generator, do not modify.
    -->
    <id column="IF_id" property="ifId" jdbcType="INTEGER" />
    <result column="IF_code" property="ifCode" jdbcType="NVARCHAR" />
    <result column="IF_name" property="ifName" jdbcType="NVARCHAR" />
    <result column="IF_cat" property="ifCat" jdbcType="NVARCHAR" />
    <result column="IF_sub_cat" property="ifSubCat" jdbcType="NVARCHAR" />
    <result column="Is_parent" property="isParent" jdbcType="BIT" />
    <result column="Parent_id" property="parentId" jdbcType="INTEGER" />
    <result column="Pj_id" property="pjId" jdbcType="BIGINT" />
    <result column="Store_id" property="storeId" jdbcType="BIGINT" />
    <result column="Role_id" property="roleId" jdbcType="INTEGER" />
    <result column="Process_index" property="processIndex" jdbcType="INTEGER" />
    <result column="Bat_no_pre" property="batNoPre" jdbcType="VARCHAR" />
    <result column="Bat_no_length" property="batNoLength" jdbcType="INTEGER" />
    <result column="Bat_no_current" property="batNoCurrent" jdbcType="INTEGER" />
    <result column="Operate_user_id" property="operateUserId" jdbcType="BIGINT" />
    <result column="Operate_time" property="operateTime" jdbcType="TIMESTAMP" />
    <result column="Create_time" property="createTime" jdbcType="TIMESTAMP" />
    <result column="Thread_num" property="threadNum" jdbcType="INTEGER" />
    <result column="Status" property="status" jdbcType="INTEGER" />
    <result column="IF_prop_1" property="ifProp1" jdbcType="VARCHAR" />
    <result column="IF_prop_2" property="ifProp2" jdbcType="VARCHAR" />
    <result column="IF_prop_3" property="ifProp3" jdbcType="VARCHAR" />
    <result column="IF_qty_1" property="ifQty1" jdbcType="INTEGER" />
    <result column="IF_qty_2" property="ifQty2" jdbcType="INTEGER" />
    <result column="IF_qty_3" property="ifQty3" jdbcType="INTEGER" />
    <result column="IF_time_1" property="ifTime1" jdbcType="TIMESTAMP" />
    <result column="IF_time_2" property="ifTime2" jdbcType="TIMESTAMP" />
    <result column="IF_time_3" property="ifTime3" jdbcType="TIMESTAMP" />
    <result column="No_data_retry_times" property="noDataRetryTimes" jdbcType="INTEGER" />
    <result column="Not_data_retry_to_seconds" property="notDataRetryToSeconds" jdbcType="INTEGER" />
    <result column="Error_retry_times" property="errorRetryTimes" jdbcType="INTEGER" />
    <result column="Error_retry_to_seconds" property="errorRetryToSeconds" jdbcType="INTEGER" />
    <result column="Retry_wait_seconds" property="retryWaitSeconds" jdbcType="INTEGER" />
    <result column="Retry_type" property="retryType" jdbcType="CHAR" />
    <result column="Fail_continue" property="failContinue" jdbcType="BIT" />
    <result column="Wait_time_out" property="waitTimeOut" jdbcType="INTEGER" />
    <result column="Time_out_continue" property="timeOutContinue" jdbcType="BIT" />
  </resultMap>
  <resultMap id="ResultMapWithBLOBs" type="com.ami.ec.channel.domain.pluginManager.IfDefine" extends="BaseResultMap" >
    <!--
      WARNING - @mbggenerated
      This element is automatically generated by MyBatis Generator, do not modify.
    -->
    <result column="Time_stamp" property="timeStamp" jdbcType="BINARY" />
  </resultMap>
  <sql id="Example_Where_Clause" >
    <!--
      WARNING - @mbggenerated
      This element is automatically generated by MyBatis Generator, do not modify.
    -->
    <where >
      <foreach collection="oredCriteria" item="criteria" separator="or" >
        <if test="criteria.valid" >
          <trim prefix="(" suffix=")" prefixOverrides="and" >
            <foreach collection="criteria.criteria" item="criterion" >
              <choose >
                <when test="criterion.noValue" >
                  and ${criterion.condition}
                </when>
                <when test="criterion.singleValue" >
                  and ${criterion.condition} #{criterion.value}
                </when>
                <when test="criterion.betweenValue" >
                  and ${criterion.condition} #{criterion.value} and #{criterion.secondValue}
                </when>
                <when test="criterion.listValue" >
                  and ${criterion.condition}
                  <foreach collection="criterion.value" item="listItem" open="(" close=")" separator="," >
                    #{listItem}
                  </foreach>
                </when>
              </choose>
            </foreach>
          </trim>
        </if>
      </foreach>
    </where>
  </sql>
  <sql id="Update_By_Example_Where_Clause" >
    <!--
      WARNING - @mbggenerated
      This element is automatically generated by MyBatis Generator, do not modify.
    -->
    <where >
      <foreach collection="example.oredCriteria" item="criteria" separator="or" >
        <if test="criteria.valid" >
          <trim prefix="(" suffix=")" prefixOverrides="and" >
            <foreach collection="criteria.criteria" item="criterion" >
              <choose >
                <when test="criterion.noValue" >
                  and ${criterion.condition}
                </when>
                <when test="criterion.singleValue" >
                  and ${criterion.condition} #{criterion.value}
                </when>
                <when test="criterion.betweenValue" >
                  and ${criterion.condition} #{criterion.value} and #{criterion.secondValue}
                </when>
                <when test="criterion.listValue" >
                  and ${criterion.condition}
                  <foreach collection="criterion.value" item="listItem" open="(" close=")" separator="," >
                    #{listItem}
                  </foreach>
                </when>
              </choose>
            </foreach>
          </trim>
        </if>
      </foreach>
    </where>
  </sql>
  <sql id="Base_Column_List" >
    <!--
      WARNING - @mbggenerated
      This element is automatically generated by MyBatis Generator, do not modify.
    -->
    IF_id, IF_code, IF_name, IF_cat, IF_sub_cat, Is_parent, Parent_id, Pj_id, Store_id, 
    Role_id, Process_index, Bat_no_pre, Bat_no_length, Bat_no_current, Operate_user_id, 
    Operate_time, Create_time, Thread_num, Status, IF_prop_1, IF_prop_2, IF_prop_3, IF_qty_1, 
    IF_qty_2, IF_qty_3, IF_time_1, IF_time_2, IF_time_3, No_data_retry_times, Not_data_retry_to_seconds, 
    Error_retry_times, Error_retry_to_seconds, Retry_wait_seconds, Retry_type, Fail_continue, 
    Wait_time_out, Time_out_continue
  </sql>
  <sql id="Blob_Column_List" >
    <!--
      WARNING - @mbggenerated
      This element is automatically generated by MyBatis Generator, do not modify.
    -->
    Time_stamp
  </sql>
  <select id="selectByExampleWithBLOBs" resultMap="ResultMapWithBLOBs" parameterType="com.ami.ec.channel.domain.pluginManager.IfDefineExample" >
    <!--
      WARNING - @mbggenerated
      This element is automatically generated by MyBatis Generator, do not modify.
    -->
    select
    <if test="distinct" >
      distinct
    </if>
    <include refid="Base_Column_List" />
    ,
    <include refid="Blob_Column_List" />
    from IF_define
    <if test="_parameter != null" >
      <include refid="Example_Where_Clause" />
    </if>
    <if test="orderByClause != null" >
      order by ${orderByClause}
    </if>
  </select>
  <select id="selectByExample" resultMap="BaseResultMap" parameterType="com.ami.ec.channel.domain.pluginManager.IfDefineExample" >
    <!--
      WARNING - @mbggenerated
      This element is automatically generated by MyBatis Generator, do not modify.
    -->
    select
    <if test="distinct" >
      distinct
    </if>
    <include refid="Base_Column_List" />
    from IF_define
    <if test="_parameter != null" >
      <include refid="Example_Where_Clause" />
    </if>
    <if test="orderByClause != null" >
      order by ${orderByClause}
    </if>
  </select>
  <select id="selectByPrimaryKey" resultMap="ResultMapWithBLOBs" parameterType="java.lang.Integer" >
    <!--
      WARNING - @mbggenerated
      This element is automatically generated by MyBatis Generator, do not modify.
    -->
    select 
    <include refid="Base_Column_List" />
    ,
    <include refid="Blob_Column_List" />
    from IF_define
    where IF_id = #{ifId,jdbcType=INTEGER}
  </select>
  <delete id="deleteByPrimaryKey" parameterType="java.lang.Integer" >
    <!--
      WARNING - @mbggenerated
      This element is automatically generated by MyBatis Generator, do not modify.
    -->
    delete from IF_define
    where IF_id = #{ifId,jdbcType=INTEGER}
  </delete>
  <delete id="deleteByExample" parameterType="com.ami.ec.channel.domain.pluginManager.IfDefineExample" >
    <!--
      WARNING - @mbggenerated
      This element is automatically generated by MyBatis Generator, do not modify.
    -->
    delete from IF_define
    <if test="_parameter != null" >
      <include refid="Example_Where_Clause" />
    </if>
  </delete>
  <insert id="insert" parameterType="com.ami.ec.channel.domain.pluginManager.IfDefine" >
    <!--
      WARNING - @mbggenerated
      This element is automatically generated by MyBatis Generator, do not modify.
    -->
    insert into IF_define (IF_id, IF_code, IF_name, 
      IF_cat, IF_sub_cat, Is_parent, 
      Parent_id, Pj_id, Store_id, 
      Role_id, Process_index, Bat_no_pre, 
      Bat_no_length, Bat_no_current, Operate_user_id, 
      Operate_time, Create_time, Thread_num, 
      Status, IF_prop_1, IF_prop_2, 
      IF_prop_3, IF_qty_1, IF_qty_2, 
      IF_qty_3, IF_time_1, IF_time_2, 
      IF_time_3, No_data_retry_times, Not_data_retry_to_seconds, 
      Error_retry_times, Error_retry_to_seconds, Retry_wait_seconds, 
      Retry_type, Fail_continue, Wait_time_out, 
      Time_out_continue, Time_stamp)
    values (#{ifId,jdbcType=INTEGER}, #{ifCode,jdbcType=NVARCHAR}, #{ifName,jdbcType=NVARCHAR}, 
      #{ifCat,jdbcType=NVARCHAR}, #{ifSubCat,jdbcType=NVARCHAR}, #{isParent,jdbcType=BIT}, 
      #{parentId,jdbcType=INTEGER}, #{pjId,jdbcType=BIGINT}, #{storeId,jdbcType=BIGINT}, 
      #{roleId,jdbcType=INTEGER}, #{processIndex,jdbcType=INTEGER}, #{batNoPre,jdbcType=VARCHAR}, 
      #{batNoLength,jdbcType=INTEGER}, #{batNoCurrent,jdbcType=INTEGER}, #{operateUserId,jdbcType=BIGINT}, 
      #{operateTime,jdbcType=TIMESTAMP}, #{createTime,jdbcType=TIMESTAMP}, #{threadNum,jdbcType=INTEGER}, 
      #{status,jdbcType=INTEGER}, #{ifProp1,jdbcType=VARCHAR}, #{ifProp2,jdbcType=VARCHAR}, 
      #{ifProp3,jdbcType=VARCHAR}, #{ifQty1,jdbcType=INTEGER}, #{ifQty2,jdbcType=INTEGER}, 
      #{ifQty3,jdbcType=INTEGER}, #{ifTime1,jdbcType=TIMESTAMP}, #{ifTime2,jdbcType=TIMESTAMP}, 
      #{ifTime3,jdbcType=TIMESTAMP}, #{noDataRetryTimes,jdbcType=INTEGER}, #{notDataRetryToSeconds,jdbcType=INTEGER}, 
      #{errorRetryTimes,jdbcType=INTEGER}, #{errorRetryToSeconds,jdbcType=INTEGER}, #{retryWaitSeconds,jdbcType=INTEGER}, 
      #{retryType,jdbcType=CHAR}, #{failContinue,jdbcType=BIT}, #{waitTimeOut,jdbcType=INTEGER}, 
      #{timeOutContinue,jdbcType=BIT}, #{timeStamp,jdbcType=BINARY})
  </insert>
  <insert id="insertSelective" parameterType="com.ami.ec.channel.domain.pluginManager.IfDefine" >
    <!--
      WARNING - @mbggenerated
      This element is automatically generated by MyBatis Generator, do not modify.
    -->
    insert into IF_define
    <trim prefix="(" suffix=")" suffixOverrides="," >
      <if test="ifId != null" >
        IF_id,
      </if>
      <if test="ifCode != null" >
        IF_code,
      </if>
      <if test="ifName != null" >
        IF_name,
      </if>
      <if test="ifCat != null" >
        IF_cat,
      </if>
      <if test="ifSubCat != null" >
        IF_sub_cat,
      </if>
      <if test="isParent != null" >
        Is_parent,
      </if>
      <if test="parentId != null" >
        Parent_id,
      </if>
      <if test="pjId != null" >
        Pj_id,
      </if>
      <if test="storeId != null" >
        Store_id,
      </if>
      <if test="roleId != null" >
        Role_id,
      </if>
      <if test="processIndex != null" >
        Process_index,
      </if>
      <if test="batNoPre != null" >
        Bat_no_pre,
      </if>
      <if test="batNoLength != null" >
        Bat_no_length,
      </if>
      <if test="batNoCurrent != null" >
        Bat_no_current,
      </if>
      <if test="operateUserId != null" >
        Operate_user_id,
      </if>
      <if test="operateTime != null" >
        Operate_time,
      </if>
      <if test="createTime != null" >
        Create_time,
      </if>
      <if test="threadNum != null" >
        Thread_num,
      </if>
      <if test="status != null" >
        Status,
      </if>
      <if test="ifProp1 != null" >
        IF_prop_1,
      </if>
      <if test="ifProp2 != null" >
        IF_prop_2,
      </if>
      <if test="ifProp3 != null" >
        IF_prop_3,
      </if>
      <if test="ifQty1 != null" >
        IF_qty_1,
      </if>
      <if test="ifQty2 != null" >
        IF_qty_2,
      </if>
      <if test="ifQty3 != null" >
        IF_qty_3,
      </if>
      <if test="ifTime1 != null" >
        IF_time_1,
      </if>
      <if test="ifTime2 != null" >
        IF_time_2,
      </if>
      <if test="ifTime3 != null" >
        IF_time_3,
      </if>
      <if test="noDataRetryTimes != null" >
        No_data_retry_times,
      </if>
      <if test="notDataRetryToSeconds != null" >
        Not_data_retry_to_seconds,
      </if>
      <if test="errorRetryTimes != null" >
        Error_retry_times,
      </if>
      <if test="errorRetryToSeconds != null" >
        Error_retry_to_seconds,
      </if>
      <if test="retryWaitSeconds != null" >
        Retry_wait_seconds,
      </if>
      <if test="retryType != null" >
        Retry_type,
      </if>
      <if test="failContinue != null" >
        Fail_continue,
      </if>
      <if test="waitTimeOut != null" >
        Wait_time_out,
      </if>
      <if test="timeOutContinue != null" >
        Time_out_continue,
      </if>
      <if test="timeStamp != null" >
        Time_stamp,
      </if>
    </trim>
    <trim prefix="values (" suffix=")" suffixOverrides="," >
      <if test="ifId != null" >
        #{ifId,jdbcType=INTEGER},
      </if>
      <if test="ifCode != null" >
        #{ifCode,jdbcType=NVARCHAR},
      </if>
      <if test="ifName != null" >
        #{ifName,jdbcType=NVARCHAR},
      </if>
      <if test="ifCat != null" >
        #{ifCat,jdbcType=NVARCHAR},
      </if>
      <if test="ifSubCat != null" >
        #{ifSubCat,jdbcType=NVARCHAR},
      </if>
      <if test="isParent != null" >
        #{isParent,jdbcType=BIT},
      </if>
      <if test="parentId != null" >
        #{parentId,jdbcType=INTEGER},
      </if>
      <if test="pjId != null" >
        #{pjId,jdbcType=BIGINT},
      </if>
      <if test="storeId != null" >
        #{storeId,jdbcType=BIGINT},
      </if>
      <if test="roleId != null" >
        #{roleId,jdbcType=INTEGER},
      </if>
      <if test="processIndex != null" >
        #{processIndex,jdbcType=INTEGER},
      </if>
      <if test="batNoPre != null" >
        #{batNoPre,jdbcType=VARCHAR},
      </if>
      <if test="batNoLength != null" >
        #{batNoLength,jdbcType=INTEGER},
      </if>
      <if test="batNoCurrent != null" >
        #{batNoCurrent,jdbcType=INTEGER},
      </if>
      <if test="operateUserId != null" >
        #{operateUserId,jdbcType=BIGINT},
      </if>
      <if test="operateTime != null" >
        #{operateTime,jdbcType=TIMESTAMP},
      </if>
      <if test="createTime != null" >
        #{createTime,jdbcType=TIMESTAMP},
      </if>
      <if test="threadNum != null" >
        #{threadNum,jdbcType=INTEGER},
      </if>
      <if test="status != null" >
        #{status,jdbcType=INTEGER},
      </if>
      <if test="ifProp1 != null" >
        #{ifProp1,jdbcType=VARCHAR},
      </if>
      <if test="ifProp2 != null" >
        #{ifProp2,jdbcType=VARCHAR},
      </if>
      <if test="ifProp3 != null" >
        #{ifProp3,jdbcType=VARCHAR},
      </if>
      <if test="ifQty1 != null" >
        #{ifQty1,jdbcType=INTEGER},
      </if>
      <if test="ifQty2 != null" >
        #{ifQty2,jdbcType=INTEGER},
      </if>
      <if test="ifQty3 != null" >
        #{ifQty3,jdbcType=INTEGER},
      </if>
      <if test="ifTime1 != null" >
        #{ifTime1,jdbcType=TIMESTAMP},
      </if>
      <if test="ifTime2 != null" >
        #{ifTime2,jdbcType=TIMESTAMP},
      </if>
      <if test="ifTime3 != null" >
        #{ifTime3,jdbcType=TIMESTAMP},
      </if>
      <if test="noDataRetryTimes != null" >
        #{noDataRetryTimes,jdbcType=INTEGER},
      </if>
      <if test="notDataRetryToSeconds != null" >
        #{notDataRetryToSeconds,jdbcType=INTEGER},
      </if>
      <if test="errorRetryTimes != null" >
        #{errorRetryTimes,jdbcType=INTEGER},
      </if>
      <if test="errorRetryToSeconds != null" >
        #{errorRetryToSeconds,jdbcType=INTEGER},
      </if>
      <if test="retryWaitSeconds != null" >
        #{retryWaitSeconds,jdbcType=INTEGER},
      </if>
      <if test="retryType != null" >
        #{retryType,jdbcType=CHAR},
      </if>
      <if test="failContinue != null" >
        #{failContinue,jdbcType=BIT},
      </if>
      <if test="waitTimeOut != null" >
        #{waitTimeOut,jdbcType=INTEGER},
      </if>
      <if test="timeOutContinue != null" >
        #{timeOutContinue,jdbcType=BIT},
      </if>
      <if test="timeStamp != null" >
        #{timeStamp,jdbcType=BINARY},
      </if>
    </trim>
  </insert>
  <select id="countByExample" parameterType="com.ami.ec.channel.domain.pluginManager.IfDefineExample" resultType="java.lang.Integer" >
    <!--
      WARNING - @mbggenerated
      This element is automatically generated by MyBatis Generator, do not modify.
    -->
    select count(*) from IF_define
    <if test="_parameter != null" >
      <include refid="Example_Where_Clause" />
    </if>
  </select>
  <update id="updateByExampleSelective" parameterType="map" >
    <!--
      WARNING - @mbggenerated
      This element is automatically generated by MyBatis Generator, do not modify.
    -->
    update IF_define
    <set >
      <if test="record.ifId != null" >
        IF_id = #{record.ifId,jdbcType=INTEGER},
      </if>
      <if test="record.ifCode != null" >
        IF_code = #{record.ifCode,jdbcType=NVARCHAR},
      </if>
      <if test="record.ifName != null" >
        IF_name = #{record.ifName,jdbcType=NVARCHAR},
      </if>
      <if test="record.ifCat != null" >
        IF_cat = #{record.ifCat,jdbcType=NVARCHAR},
      </if>
      <if test="record.ifSubCat != null" >
        IF_sub_cat = #{record.ifSubCat,jdbcType=NVARCHAR},
      </if>
      <if test="record.isParent != null" >
        Is_parent = #{record.isParent,jdbcType=BIT},
      </if>
      <if test="record.parentId != null" >
        Parent_id = #{record.parentId,jdbcType=INTEGER},
      </if>
      <if test="record.pjId != null" >
        Pj_id = #{record.pjId,jdbcType=BIGINT},
      </if>
      <if test="record.storeId != null" >
        Store_id = #{record.storeId,jdbcType=BIGINT},
      </if>
      <if test="record.roleId != null" >
        Role_id = #{record.roleId,jdbcType=INTEGER},
      </if>
      <if test="record.processIndex != null" >
        Process_index = #{record.processIndex,jdbcType=INTEGER},
      </if>
      <if test="record.batNoPre != null" >
        Bat_no_pre = #{record.batNoPre,jdbcType=VARCHAR},
      </if>
      <if test="record.batNoLength != null" >
        Bat_no_length = #{record.batNoLength,jdbcType=INTEGER},
      </if>
      <if test="record.batNoCurrent != null" >
        Bat_no_current = #{record.batNoCurrent,jdbcType=INTEGER},
      </if>
      <if test="record.operateUserId != null" >
        Operate_user_id = #{record.operateUserId,jdbcType=BIGINT},
      </if>
      <if test="record.operateTime != null" >
        Operate_time = #{record.operateTime,jdbcType=TIMESTAMP},
      </if>
      <if test="record.createTime != null" >
        Create_time = #{record.createTime,jdbcType=TIMESTAMP},
      </if>
      <if test="record.threadNum != null" >
        Thread_num = #{record.threadNum,jdbcType=INTEGER},
      </if>
      <if test="record.status != null" >
        Status = #{record.status,jdbcType=INTEGER},
      </if>
      <if test="record.ifProp1 != null" >
        IF_prop_1 = #{record.ifProp1,jdbcType=VARCHAR},
      </if>
      <if test="record.ifProp2 != null" >
        IF_prop_2 = #{record.ifProp2,jdbcType=VARCHAR},
      </if>
      <if test="record.ifProp3 != null" >
        IF_prop_3 = #{record.ifProp3,jdbcType=VARCHAR},
      </if>
      <if test="record.ifQty1 != null" >
        IF_qty_1 = #{record.ifQty1,jdbcType=INTEGER},
      </if>
      <if test="record.ifQty2 != null" >
        IF_qty_2 = #{record.ifQty2,jdbcType=INTEGER},
      </if>
      <if test="record.ifQty3 != null" >
        IF_qty_3 = #{record.ifQty3,jdbcType=INTEGER},
      </if>
      <if test="record.ifTime1 != null" >
        IF_time_1 = #{record.ifTime1,jdbcType=TIMESTAMP},
      </if>
      <if test="record.ifTime2 != null" >
        IF_time_2 = #{record.ifTime2,jdbcType=TIMESTAMP},
      </if>
      <if test="record.ifTime3 != null" >
        IF_time_3 = #{record.ifTime3,jdbcType=TIMESTAMP},
      </if>
      <if test="record.noDataRetryTimes != null" >
        No_data_retry_times = #{record.noDataRetryTimes,jdbcType=INTEGER},
      </if>
      <if test="record.notDataRetryToSeconds != null" >
        Not_data_retry_to_seconds = #{record.notDataRetryToSeconds,jdbcType=INTEGER},
      </if>
      <if test="record.errorRetryTimes != null" >
        Error_retry_times = #{record.errorRetryTimes,jdbcType=INTEGER},
      </if>
      <if test="record.errorRetryToSeconds != null" >
        Error_retry_to_seconds = #{record.errorRetryToSeconds,jdbcType=INTEGER},
      </if>
      <if test="record.retryWaitSeconds != null" >
        Retry_wait_seconds = #{record.retryWaitSeconds,jdbcType=INTEGER},
      </if>
      <if test="record.retryType != null" >
        Retry_type = #{record.retryType,jdbcType=CHAR},
      </if>
      <if test="record.failContinue != null" >
        Fail_continue = #{record.failContinue,jdbcType=BIT},
      </if>
      <if test="record.waitTimeOut != null" >
        Wait_time_out = #{record.waitTimeOut,jdbcType=INTEGER},
      </if>
      <if test="record.timeOutContinue != null" >
        Time_out_continue = #{record.timeOutContinue,jdbcType=BIT},
      </if>
      <if test="record.timeStamp != null" >
        Time_stamp = #{record.timeStamp,jdbcType=BINARY},
      </if>
    </set>
    <if test="_parameter != null" >
      <include refid="Update_By_Example_Where_Clause" />
    </if>
  </update>
  <update id="updateByExampleWithBLOBs" parameterType="map" >
    <!--
      WARNING - @mbggenerated
      This element is automatically generated by MyBatis Generator, do not modify.
    -->
    update IF_define
    set IF_id = #{record.ifId,jdbcType=INTEGER},
      IF_code = #{record.ifCode,jdbcType=NVARCHAR},
      IF_name = #{record.ifName,jdbcType=NVARCHAR},
      IF_cat = #{record.ifCat,jdbcType=NVARCHAR},
      IF_sub_cat = #{record.ifSubCat,jdbcType=NVARCHAR},
      Is_parent = #{record.isParent,jdbcType=BIT},
      Parent_id = #{record.parentId,jdbcType=INTEGER},
      Pj_id = #{record.pjId,jdbcType=BIGINT},
      Store_id = #{record.storeId,jdbcType=BIGINT},
      Role_id = #{record.roleId,jdbcType=INTEGER},
      Process_index = #{record.processIndex,jdbcType=INTEGER},
      Bat_no_pre = #{record.batNoPre,jdbcType=VARCHAR},
      Bat_no_length = #{record.batNoLength,jdbcType=INTEGER},
      Bat_no_current = #{record.batNoCurrent,jdbcType=INTEGER},
      Operate_user_id = #{record.operateUserId,jdbcType=BIGINT},
      Operate_time = #{record.operateTime,jdbcType=TIMESTAMP},
      Create_time = #{record.createTime,jdbcType=TIMESTAMP},
      Thread_num = #{record.threadNum,jdbcType=INTEGER},
      Status = #{record.status,jdbcType=INTEGER},
      IF_prop_1 = #{record.ifProp1,jdbcType=VARCHAR},
      IF_prop_2 = #{record.ifProp2,jdbcType=VARCHAR},
      IF_prop_3 = #{record.ifProp3,jdbcType=VARCHAR},
      IF_qty_1 = #{record.ifQty1,jdbcType=INTEGER},
      IF_qty_2 = #{record.ifQty2,jdbcType=INTEGER},
      IF_qty_3 = #{record.ifQty3,jdbcType=INTEGER},
      IF_time_1 = #{record.ifTime1,jdbcType=TIMESTAMP},
      IF_time_2 = #{record.ifTime2,jdbcType=TIMESTAMP},
      IF_time_3 = #{record.ifTime3,jdbcType=TIMESTAMP},
      No_data_retry_times = #{record.noDataRetryTimes,jdbcType=INTEGER},
      Not_data_retry_to_seconds = #{record.notDataRetryToSeconds,jdbcType=INTEGER},
      Error_retry_times = #{record.errorRetryTimes,jdbcType=INTEGER},
      Error_retry_to_seconds = #{record.errorRetryToSeconds,jdbcType=INTEGER},
      Retry_wait_seconds = #{record.retryWaitSeconds,jdbcType=INTEGER},
      Retry_type = #{record.retryType,jdbcType=CHAR},
      Fail_continue = #{record.failContinue,jdbcType=BIT},
      Wait_time_out = #{record.waitTimeOut,jdbcType=INTEGER},
      Time_out_continue = #{record.timeOutContinue,jdbcType=BIT},
      Time_stamp = #{record.timeStamp,jdbcType=BINARY}
    <if test="_parameter != null" >
      <include refid="Update_By_Example_Where_Clause" />
    </if>
  </update>
  <update id="updateByExample" parameterType="map" >
    <!--
      WARNING - @mbggenerated
      This element is automatically generated by MyBatis Generator, do not modify.
    -->
    update IF_define
    set IF_id = #{record.ifId,jdbcType=INTEGER},
      IF_code = #{record.ifCode,jdbcType=NVARCHAR},
      IF_name = #{record.ifName,jdbcType=NVARCHAR},
      IF_cat = #{record.ifCat,jdbcType=NVARCHAR},
      IF_sub_cat = #{record.ifSubCat,jdbcType=NVARCHAR},
      Is_parent = #{record.isParent,jdbcType=BIT},
      Parent_id = #{record.parentId,jdbcType=INTEGER},
      Pj_id = #{record.pjId,jdbcType=BIGINT},
      Store_id = #{record.storeId,jdbcType=BIGINT},
      Role_id = #{record.roleId,jdbcType=INTEGER},
      Process_index = #{record.processIndex,jdbcType=INTEGER},
      Bat_no_pre = #{record.batNoPre,jdbcType=VARCHAR},
      Bat_no_length = #{record.batNoLength,jdbcType=INTEGER},
      Bat_no_current = #{record.batNoCurrent,jdbcType=INTEGER},
      Operate_user_id = #{record.operateUserId,jdbcType=BIGINT},
      Operate_time = #{record.operateTime,jdbcType=TIMESTAMP},
      Create_time = #{record.createTime,jdbcType=TIMESTAMP},
      Thread_num = #{record.threadNum,jdbcType=INTEGER},
      Status = #{record.status,jdbcType=INTEGER},
      IF_prop_1 = #{record.ifProp1,jdbcType=VARCHAR},
      IF_prop_2 = #{record.ifProp2,jdbcType=VARCHAR},
      IF_prop_3 = #{record.ifProp3,jdbcType=VARCHAR},
      IF_qty_1 = #{record.ifQty1,jdbcType=INTEGER},
      IF_qty_2 = #{record.ifQty2,jdbcType=INTEGER},
      IF_qty_3 = #{record.ifQty3,jdbcType=INTEGER},
      IF_time_1 = #{record.ifTime1,jdbcType=TIMESTAMP},
      IF_time_2 = #{record.ifTime2,jdbcType=TIMESTAMP},
      IF_time_3 = #{record.ifTime3,jdbcType=TIMESTAMP},
      No_data_retry_times = #{record.noDataRetryTimes,jdbcType=INTEGER},
      Not_data_retry_to_seconds = #{record.notDataRetryToSeconds,jdbcType=INTEGER},
      Error_retry_times = #{record.errorRetryTimes,jdbcType=INTEGER},
      Error_retry_to_seconds = #{record.errorRetryToSeconds,jdbcType=INTEGER},
      Retry_wait_seconds = #{record.retryWaitSeconds,jdbcType=INTEGER},
      Retry_type = #{record.retryType,jdbcType=CHAR},
      Fail_continue = #{record.failContinue,jdbcType=BIT},
      Wait_time_out = #{record.waitTimeOut,jdbcType=INTEGER},
      Time_out_continue = #{record.timeOutContinue,jdbcType=BIT}
    <if test="_parameter != null" >
      <include refid="Update_By_Example_Where_Clause" />
    </if>
  </update>
  <update id="updateByPrimaryKeySelective" parameterType="com.ami.ec.channel.domain.pluginManager.IfDefine" >
    <!--
      WARNING - @mbggenerated
      This element is automatically generated by MyBatis Generator, do not modify.
    -->
    update IF_define
    <set >
      <if test="ifCode != null" >
        IF_code = #{ifCode,jdbcType=NVARCHAR},
      </if>
      <if test="ifName != null" >
        IF_name = #{ifName,jdbcType=NVARCHAR},
      </if>
      <if test="ifCat != null" >
        IF_cat = #{ifCat,jdbcType=NVARCHAR},
      </if>
      <if test="ifSubCat != null" >
        IF_sub_cat = #{ifSubCat,jdbcType=NVARCHAR},
      </if>
      <if test="isParent != null" >
        Is_parent = #{isParent,jdbcType=BIT},
      </if>
      <if test="parentId != null" >
        Parent_id = #{parentId,jdbcType=INTEGER},
      </if>
      <if test="pjId != null" >
        Pj_id = #{pjId,jdbcType=BIGINT},
      </if>
      <if test="storeId != null" >
        Store_id = #{storeId,jdbcType=BIGINT},
      </if>
      <if test="roleId != null" >
        Role_id = #{roleId,jdbcType=INTEGER},
      </if>
      <if test="processIndex != null" >
        Process_index = #{processIndex,jdbcType=INTEGER},
      </if>
      <if test="batNoPre != null" >
        Bat_no_pre = #{batNoPre,jdbcType=VARCHAR},
      </if>
      <if test="batNoLength != null" >
        Bat_no_length = #{batNoLength,jdbcType=INTEGER},
      </if>
      <if test="batNoCurrent != null" >
        Bat_no_current = #{batNoCurrent,jdbcType=INTEGER},
      </if>
      <if test="operateUserId != null" >
        Operate_user_id = #{operateUserId,jdbcType=BIGINT},
      </if>
      <if test="operateTime != null" >
        Operate_time = #{operateTime,jdbcType=TIMESTAMP},
      </if>
      <if test="createTime != null" >
        Create_time = #{createTime,jdbcType=TIMESTAMP},
      </if>
      <if test="threadNum != null" >
        Thread_num = #{threadNum,jdbcType=INTEGER},
      </if>
      <if test="status != null" >
        Status = #{status,jdbcType=INTEGER},
      </if>
      <if test="ifProp1 != null" >
        IF_prop_1 = #{ifProp1,jdbcType=VARCHAR},
      </if>
      <if test="ifProp2 != null" >
        IF_prop_2 = #{ifProp2,jdbcType=VARCHAR},
      </if>
      <if test="ifProp3 != null" >
        IF_prop_3 = #{ifProp3,jdbcType=VARCHAR},
      </if>
      <if test="ifQty1 != null" >
        IF_qty_1 = #{ifQty1,jdbcType=INTEGER},
      </if>
      <if test="ifQty2 != null" >
        IF_qty_2 = #{ifQty2,jdbcType=INTEGER},
      </if>
      <if test="ifQty3 != null" >
        IF_qty_3 = #{ifQty3,jdbcType=INTEGER},
      </if>
      <if test="ifTime1 != null" >
        IF_time_1 = #{ifTime1,jdbcType=TIMESTAMP},
      </if>
      <if test="ifTime2 != null" >
        IF_time_2 = #{ifTime2,jdbcType=TIMESTAMP},
      </if>
      <if test="ifTime3 != null" >
        IF_time_3 = #{ifTime3,jdbcType=TIMESTAMP},
      </if>
      <if test="noDataRetryTimes != null" >
        No_data_retry_times = #{noDataRetryTimes,jdbcType=INTEGER},
      </if>
      <if test="notDataRetryToSeconds != null" >
        Not_data_retry_to_seconds = #{notDataRetryToSeconds,jdbcType=INTEGER},
      </if>
      <if test="errorRetryTimes != null" >
        Error_retry_times = #{errorRetryTimes,jdbcType=INTEGER},
      </if>
      <if test="errorRetryToSeconds != null" >
        Error_retry_to_seconds = #{errorRetryToSeconds,jdbcType=INTEGER},
      </if>
      <if test="retryWaitSeconds != null" >
        Retry_wait_seconds = #{retryWaitSeconds,jdbcType=INTEGER},
      </if>
      <if test="retryType != null" >
        Retry_type = #{retryType,jdbcType=CHAR},
      </if>
      <if test="failContinue != null" >
        Fail_continue = #{failContinue,jdbcType=BIT},
      </if>
      <if test="waitTimeOut != null" >
        Wait_time_out = #{waitTimeOut,jdbcType=INTEGER},
      </if>
      <if test="timeOutContinue != null" >
        Time_out_continue = #{timeOutContinue,jdbcType=BIT},
      </if>
      <if test="timeStamp != null" >
        Time_stamp = #{timeStamp,jdbcType=BINARY},
      </if>
    </set>
    where IF_id = #{ifId,jdbcType=INTEGER}
  </update>
  <update id="updateByPrimaryKeyWithBLOBs" parameterType="com.ami.ec.channel.domain.pluginManager.IfDefine" >
    <!--
      WARNING - @mbggenerated
      This element is automatically generated by MyBatis Generator, do not modify.
    -->
    update IF_define
    set IF_code = #{ifCode,jdbcType=NVARCHAR},
      IF_name = #{ifName,jdbcType=NVARCHAR},
      IF_cat = #{ifCat,jdbcType=NVARCHAR},
      IF_sub_cat = #{ifSubCat,jdbcType=NVARCHAR},
      Is_parent = #{isParent,jdbcType=BIT},
      Parent_id = #{parentId,jdbcType=INTEGER},
      Pj_id = #{pjId,jdbcType=BIGINT},
      Store_id = #{storeId,jdbcType=BIGINT},
      Role_id = #{roleId,jdbcType=INTEGER},
      Process_index = #{processIndex,jdbcType=INTEGER},
      Bat_no_pre = #{batNoPre,jdbcType=VARCHAR},
      Bat_no_length = #{batNoLength,jdbcType=INTEGER},
      Bat_no_current = #{batNoCurrent,jdbcType=INTEGER},
      Operate_user_id = #{operateUserId,jdbcType=BIGINT},
      Operate_time = #{operateTime,jdbcType=TIMESTAMP},
      Create_time = #{createTime,jdbcType=TIMESTAMP},
      Thread_num = #{threadNum,jdbcType=INTEGER},
      Status = #{status,jdbcType=INTEGER},
      IF_prop_1 = #{ifProp1,jdbcType=VARCHAR},
      IF_prop_2 = #{ifProp2,jdbcType=VARCHAR},
      IF_prop_3 = #{ifProp3,jdbcType=VARCHAR},
      IF_qty_1 = #{ifQty1,jdbcType=INTEGER},
      IF_qty_2 = #{ifQty2,jdbcType=INTEGER},
      IF_qty_3 = #{ifQty3,jdbcType=INTEGER},
      IF_time_1 = #{ifTime1,jdbcType=TIMESTAMP},
      IF_time_2 = #{ifTime2,jdbcType=TIMESTAMP},
      IF_time_3 = #{ifTime3,jdbcType=TIMESTAMP},
      No_data_retry_times = #{noDataRetryTimes,jdbcType=INTEGER},
      Not_data_retry_to_seconds = #{notDataRetryToSeconds,jdbcType=INTEGER},
      Error_retry_times = #{errorRetryTimes,jdbcType=INTEGER},
      Error_retry_to_seconds = #{errorRetryToSeconds,jdbcType=INTEGER},
      Retry_wait_seconds = #{retryWaitSeconds,jdbcType=INTEGER},
      Retry_type = #{retryType,jdbcType=CHAR},
      Fail_continue = #{failContinue,jdbcType=BIT},
      Wait_time_out = #{waitTimeOut,jdbcType=INTEGER},
      Time_out_continue = #{timeOutContinue,jdbcType=BIT},
      Time_stamp = #{timeStamp,jdbcType=BINARY}
    where IF_id = #{ifId,jdbcType=INTEGER}
  </update>
  <update id="updateByPrimaryKey" parameterType="com.ami.ec.channel.domain.pluginManager.IfDefine" >
    <!--
      WARNING - @mbggenerated
      This element is automatically generated by MyBatis Generator, do not modify.
    -->
    update IF_define
    set IF_code = #{ifCode,jdbcType=NVARCHAR},
      IF_name = #{ifName,jdbcType=NVARCHAR},
      IF_cat = #{ifCat,jdbcType=NVARCHAR},
      IF_sub_cat = #{ifSubCat,jdbcType=NVARCHAR},
      Is_parent = #{isParent,jdbcType=BIT},
      Parent_id = #{parentId,jdbcType=INTEGER},
      Pj_id = #{pjId,jdbcType=BIGINT},
      Store_id = #{storeId,jdbcType=BIGINT},
      Role_id = #{roleId,jdbcType=INTEGER},
      Process_index = #{processIndex,jdbcType=INTEGER},
      Bat_no_pre = #{batNoPre,jdbcType=VARCHAR},
      Bat_no_length = #{batNoLength,jdbcType=INTEGER},
      Bat_no_current = #{batNoCurrent,jdbcType=INTEGER},
      Operate_user_id = #{operateUserId,jdbcType=BIGINT},
      Operate_time = #{operateTime,jdbcType=TIMESTAMP},
      Create_time = #{createTime,jdbcType=TIMESTAMP},
      Thread_num = #{threadNum,jdbcType=INTEGER},
      Status = #{status,jdbcType=INTEGER},
      IF_prop_1 = #{ifProp1,jdbcType=VARCHAR},
      IF_prop_2 = #{ifProp2,jdbcType=VARCHAR},
      IF_prop_3 = #{ifProp3,jdbcType=VARCHAR},
      IF_qty_1 = #{ifQty1,jdbcType=INTEGER},
      IF_qty_2 = #{ifQty2,jdbcType=INTEGER},
      IF_qty_3 = #{ifQty3,jdbcType=INTEGER},
      IF_time_1 = #{ifTime1,jdbcType=TIMESTAMP},
      IF_time_2 = #{ifTime2,jdbcType=TIMESTAMP},
      IF_time_3 = #{ifTime3,jdbcType=TIMESTAMP},
      No_data_retry_times = #{noDataRetryTimes,jdbcType=INTEGER},
      Not_data_retry_to_seconds = #{notDataRetryToSeconds,jdbcType=INTEGER},
      Error_retry_times = #{errorRetryTimes,jdbcType=INTEGER},
      Error_retry_to_seconds = #{errorRetryToSeconds,jdbcType=INTEGER},
      Retry_wait_seconds = #{retryWaitSeconds,jdbcType=INTEGER},
      Retry_type = #{retryType,jdbcType=CHAR},
      Fail_continue = #{failContinue,jdbcType=BIT},
      Wait_time_out = #{waitTimeOut,jdbcType=INTEGER},
      Time_out_continue = #{timeOutContinue,jdbcType=BIT}
    where IF_id = #{ifId,jdbcType=INTEGER}
  </update>
</mapper>